switchboard/__init__.py
switchboard/__version__.py
switchboard/client.py
switchboard/config.py
switchboard/exceptions.py
switchboard/utils.py
switchboard/providers/__init__.py
switchboard/providers/anthropic_provider.py
switchboard/providers/base.py
switchboard/providers/openai_provider.py
switchboard/providers/registry.py
switchboard_ai-0.1.0.dist-info/licenses/LICENSE
switchboard_ai-0.1.0.dist-info/METADATA
switchboard_ai-0.1.0.dist-info/WHEEL
switchboard_ai-0.1.0.dist-info/top_level.txt
switchboard_ai-0.1.0.dist-info/RECORD
